fss/__init__.py
fss/extension.py
fss/security.py
fss/exception/__init__.py
fss/exception/parameter.py
fss/exception/rule.py
fss/generator/__init__.py
fss/generator/definition.py
fss/generator/generator.py
fss/generator/openapi.py
fss/generator/path.py
fss/generator/type/__init__.py
fss/generator/type/parameter.py
fss/generator/type/response.py
fss/generator/type/type.py
fss/parser/__init__.py
fss/parser/doc.py
fss/parser/rule/__init__.py
fss/parser/rule/parameter.py
fss/parser/rule/parser.py
fss/parser/rule/response.py
fss/parser/rule/rule.py
fss/parser/rule/tag.py
fss/schema/__init__.py
fss/schema/doc.py
fss/schema/method.py
fss/schema/schema.py
fss/schema/security.py
fss/schema/openapi/__init__.py
fss/schema/openapi/definition.py
fss/schema/openapi/info.py
fss/schema/openapi/item.py
fss/schema/openapi/method.py
fss/schema/openapi/openapi.py
fss/schema/openapi/parameter.py
fss/schema/openapi/response.py
fss/schema/openapi/route.py
fss/schema/openapi/schema.py
fss/schema/openapi/security.py
fss/schema/rule/__init__.py
fss/schema/rule/parameter.py
fss/schema/rule/response.py
fss/schema/rule/rule.py
fss/schema/rule/tag.py
fss/schema/rule/type.py
fss/static/favicon-16x16.png
fss/static/favicon-32x32.png
fss/static/index.css
fss/static/index.html
fss/static/oauth2-redirect.html
fss/static/swagger-ui-bundle.js
fss/static/swagger-ui-bundle.js.map
fss/static/swagger-ui-es-bundle-core.js
fss/static/swagger-ui-es-bundle-core.js.map
fss/static/swagger-ui-es-bundle.js
fss/static/swagger-ui-es-bundle.js.map
fss/static/swagger-ui-standalone-preset.js
fss/static/swagger-ui-standalone-preset.js.map
fss/static/swagger-ui.css
fss/static/swagger-ui.css.map
fss/static/swagger-ui.js
fss/static/swagger-ui.js.map
fss/util/__init__.py
fss/util/json.py
fss/view/__init__.py
fss/view/view.py
flask_schematics_swagger-0.0.6.dist-info/METADATA
flask_schematics_swagger-0.0.6.dist-info/WHEEL
flask_schematics_swagger-0.0.6.dist-info/top_level.txt
flask_schematics_swagger-0.0.6.dist-info/RECORD
