Metadata-Version: 2.1
Name: flask-schematics-swagger
Version: 0.0.6
Summary: Flask Swagger generator for Schematics models.
Home-page: https://github.com/trk54ylmz/flask-schematics-swagger
Author: Tarik Yilmaz
Author-email: tarikyilmaz.54@gmail.com
Classifier: Development Status :: 3 - Alpha
Classifier: Operating System :: MacOS
Classifier: Operating System :: Microsoft :: Windows
Classifier: Operating System :: POSIX :: Linux
Classifier: Programming Language :: Python
Classifier: Programming Language :: Python :: 3 :: Only
Classifier: Programming Language :: Python :: 3.7
Classifier: Programming Language :: Python :: 3.8
Classifier: Programming Language :: Python :: 3.9
Classifier: Programming Language :: Python :: 3.10
Requires-Python: >=3.7
Requires-Dist: schematics (>=2.1.1)
Requires-Dist: flask (>=2.0.0)
Requires-Dist: wtforms (>=2.2)
Requires-Dist: typing-extensions (>=3.7.4.3)
